owq_tools/__init__.py
owq_tools/robot.py
owq_tools-0.0.2.dist-info/METADATA
owq_tools-0.0.2.dist-info/WHEEL
owq_tools-0.0.2.dist-info/top_level.txt
owq_tools-0.0.2.dist-info/RECORD
