Metadata-Version: 2.1
Name: owq-tools
Version: 0.0.2
Summary: owq tool
Home-page: https://owq.world
Author: owq
Author-email: qaqiowo@gmail.com
Classifier: Development Status :: 1 - Planning
Classifier: Programming Language :: Python :: 3.10
Classifier: License :: OSI Approved :: MIT License
Classifier: Operating System :: OS Independent
